moldenViz/__about__.py
moldenViz/__init__.py
moldenViz/_cli.py
moldenViz/_config_module.py
moldenViz/_plotting_objects.py
moldenViz/parser.py
moldenViz/plotter.py
moldenViz/tabulator.py
moldenViz/default_configs/atom_types.json
moldenViz/default_configs/config.toml
moldenViz/examples/__init__.py
moldenViz/examples/get_example_files.py
moldenViz/examples/molden_files/acrolein.inp
moldenViz/examples/molden_files/benzene.inp
moldenViz/examples/molden_files/co.inp
moldenViz/examples/molden_files/co2.inp
moldenViz/examples/molden_files/furan.inp
moldenViz/examples/molden_files/h2o.inp
moldenViz/examples/molden_files/o2.inp
moldenViz/examples/molden_files/prismane.inp
moldenViz/examples/molden_files/pyridine.inp
moldenviz-1.8.2.dist-info/METADATA
moldenviz-1.8.2.dist-info/WHEEL
moldenviz-1.8.2.dist-info/entry_points.txt
moldenviz-1.8.2.dist-info/licenses/LICENSE
moldenviz-1.8.2.dist-info/RECORD
