Metadata-Version: 2.4
Name: moldenViz
Version: 1.8.2
Project-URL: Documentation, https://moldenviz.readthedocs.io/en/latest/
Project-URL: Issues, https://github.com/Faria22/moldenViz/issues
Project-URL: Source, https://github.com/Faria22/moldenViz
Author-email: Faria22 <fariafelipe22@hotmail.com>
License-Expression: MIT
License-File: LICENSE
Classifier: Development Status :: 5 - Production/Stable
Classifier: Programming Language :: Python
Classifier: Programming Language :: Python :: 3.10
Classifier: Programming Language :: Python :: 3.11
Classifier: Programming Language :: Python :: 3.12
Classifier: Programming Language :: Python :: 3.13
Classifier: Programming Language :: Python :: Implementation :: CPython
Classifier: Programming Language :: Python :: Implementation :: PyPy
Requires-Python: <3.14,>=3.10
Requires-Dist: numpy>=1.20
Requires-Dist: pydantic>=2.0.0
Requires-Dist: pydata-sphinx-theme>=0.14
Requires-Dist: pyqt5
Requires-Dist: pyside6
Requires-Dist: pyvista>=0.44
Requires-Dist: pyvistaqt>=0.10
Requires-Dist: scipy>=1.7
Requires-Dist: sphinx>=7.0
Requires-Dist: toml
